{
  "main": {
    "id": "efef96c344182d7e",
    "type": "split",
    "children": [
      {
        "id": "4f86756b97bd0ce7",
        "type": "tabs",
        "children": [
          {
            "id": "345604caf57b5cc0",
            "type": "leaf",
            "state": {
              "type": "markdown",
              "state": {
                "file": "PacketTracer/Esercizio01.md",
                "mode": "source",
                "source": false
              },
              "icon": "lucide-file",
              "title": "Esercizio01"
            }
          }
        ]
      }
    ],
    "direction": "vertical"
  },
  "left": {
    "id": "ddd6a53fcfbe2f8d",
    "type": "split",
    "children": [
      {
        "id": "5b3873c4d7a0cbc6",
        "type": "tabs",
        "children": [
          {
            "id": "bb7a0ab6b0c91d59",
            "type": "leaf",
            "state": {
              "type": "file-explorer",
              "state": {
                "sortOrder": "alphabetical",
                "autoReveal": false
              },
              "icon": "lucide-folder-closed",
              "title": "Esplora risorse"
            }
          },
          {
            "id": "c61ec47d22d6ef0f",
            "type": "leaf",
            "state": {
              "type": "search",
              "state": {
                "query": "",
                "matchingCase": false,
                "explainSearch": false,
                "collapseAll": false,
                "extraContext": false,
                "sortOrder": "alphabetical"
              },
              "icon": "lucide-search",
              "title": "Ricerca"
            }
          },
          {
            "id": "80030af82e14fb90",
            "type": "leaf",
            "state": {
              "type": "bookmarks",
              "state": {},
              "icon": "lucide-bookmark",
              "title": "Segnalibri"
            }
          }
        ]
      }
    ],
    "direction": "horizontal",
    "width": 300
  },
  "right": {
    "id": "9e61b7abb9a3da74",
    "type": "split",
    "children": [
      {
        "id": "d3f70312cd71c0ac",
        "type": "tabs",
        "children": [
          {
            "id": "2f899f2f9712772f",
            "type": "leaf",
            "state": {
              "type": "backlink",
              "state": {
                "collapseAll": false,
                "extraContext": false,
                "sortOrder": "alphabetical",
                "showSearch": false,
                "searchQuery": "",
                "backlinkCollapsed": false,
                "unlinkedCollapsed": true
              },
              "icon": "links-coming-in",
              "title": "Riferimenti"
            }
          },
          {
            "id": "b1f014b7c7e9547d",
            "type": "leaf",
            "state": {
              "type": "outgoing-link",
              "state": {
                "linksCollapsed": false,
                "unlinkedCollapsed": true
              },
              "icon": "links-going-out",
              "title": "Collegamenti in uscita"
            }
          },
          {
            "id": "9bdf62e8875973ac",
            "type": "leaf",
            "state": {
              "type": "tag",
              "state": {
                "sortOrder": "frequency",
                "useHierarchy": true,
                "showSearch": false,
                "searchQuery": ""
              },
              "icon": "lucide-tags",
              "title": "Etichette"
            }
          },
          {
            "id": "cea6feeea699f5f5",
            "type": "leaf",
            "state": {
              "type": "all-properties",
              "state": {
                "sortOrder": "frequency",
                "showSearch": false,
                "searchQuery": ""
              },
              "icon": "lucide-archive",
              "title": "Tutte le proprietà"
            }
          },
          {
            "id": "5807c2b23d5ab44f",
            "type": "leaf",
            "state": {
              "type": "outline",
              "state": {
                "followCursor": false,
                "showSearch": false,
                "searchQuery": ""
              },
              "icon": "lucide-list",
              "title": "Struttura"
            }
          }
        ]
      }
    ],
    "direction": "horizontal",
    "width": 300,
    "collapsed": true
  },
  "left-ribbon": {
    "hiddenItems": {
      "switcher:Apri selezione rapida": false,
      "graph:Apri vista grafo": false,
      "canvas:Crea nuova lavagna": false,
      "daily-notes:Apri nota del giorno": false,
      "templates:Inserisci modello": false,
      "command-palette:Apri riquadro comandi": false,
      "bases:Crea nuova Base": false
    }
  },
  "active": "345604caf57b5cc0",
  "lastOpenFiles": [
    "Pasted image 20260120114046.png",
    "PacketTracer/Comandi CLI.md",
    "immagini/WhatsApp Image 2026-01-20 at 11.37.34 1.jpeg",
    "README.md",
    "WhatsApp Image 2026-01-20 at 11.37.34.jpeg",
    "PacketTracer/Esercizio01.md",
    "Sistemi e reti/Lo strato applicazione/Il WWW/WWW.md",
    "Sistemi e reti/Lo strato applicazione/Il WWW/URI.md",
    "Sistemi e reti/Lo strato applicazione/Il WWW/URL.md",
    "Sistemi e reti/Lo strato applicazione/Il WWW/Pagina web Statica.md",
    "Sistemi e reti/Lo strato applicazione/Il WWW/Pagina web Dinamica.md",
    "Sistemi e reti/Lo strato applicazione/Il WWW/Deep web.md",
    "Sistemi e reti/Lo strato applicazione/Protocolli/Protocolli del livello applicazione.md",
    "Sistemi e reti/Lo strato applicazione/Protocolli/FTP.md",
    "protocollo IP.md",
    "Sistemi e reti/Lo strato di trasporto/UDP/Protocollo UDP.md",
    "Sistemi e reti/Lo strato di trasporto/UDP/Intestazione UDP.md"
  ]
}